prodigy_teams_recipes_sdk/__init__.py
prodigy_teams_recipes_sdk/__main__.py
prodigy_teams_recipes_sdk/about.json
prodigy_teams_recipes_sdk/about.py
prodigy_teams_recipes_sdk/testing.py
prodigy_teams_recipes_sdk/types.py
prodigy_teams_recipes_sdk/engine/__init__.py
prodigy_teams_recipes_sdk/engine/cli.py
prodigy_teams_recipes_sdk/engine/preview.py
prodigy_teams_recipes_sdk/engine/recipe.py
prodigy_teams_recipes_sdk/engine/recipe_loader.py
prodigy_teams_recipes_sdk/engine/recipe_schema.py
prodigy_teams_recipes_sdk/engine/registry.py
prodigy_teams_recipes_sdk/engine/teams_type.py
prodigy_teams_recipes_sdk/engine/util.py
prodigy_teams_recipes_sdk/engine/public/200.html
prodigy_teams_recipes_sdk/engine/public/200.html.br
prodigy_teams_recipes_sdk/engine/public/200.html.gz
prodigy_teams_recipes_sdk/engine/public/404.html
prodigy_teams_recipes_sdk/engine/public/404.html.br
prodigy_teams_recipes_sdk/engine/public/404.html.gz
prodigy_teams_recipes_sdk/engine/public/index.html
prodigy_teams_recipes_sdk/engine/public/index.html.br
prodigy_teams_recipes_sdk/engine/public/index.html.gz
prodigy_teams_recipes_sdk/engine/public/_nuxt/entry.86a5c951.css
prodigy_teams_recipes_sdk/engine/public/_nuxt/entry.86a5c951.css.br
prodigy_teams_recipes_sdk/engine/public/_nuxt/entry.86a5c951.css.gz
prodigy_teams_recipes_sdk/engine/public/_nuxt/entry.92243da9.js
prodigy_teams_recipes_sdk/engine/public/_nuxt/entry.92243da9.js.br
prodigy_teams_recipes_sdk/engine/public/_nuxt/entry.92243da9.js.gz
prodigy_teams_recipes_sdk/prodigy_teams_pam_sdk/__init__.py
prodigy_teams_recipes_sdk/prodigy_teams_pam_sdk/errors.py
prodigy_teams_recipes_sdk/prodigy_teams_pam_sdk/models.py
prodigy_teams_recipes_sdk/prodigy_teams_pam_sdk/recipe_client.py
prodigy_teams_recipes_sdk/prodigy_teams_pam_sdk/recipe_utils.py
prodigy_teams_recipes_sdk/prodigy_teams_pam_sdk/ty.py
prodigy_teams_recipes_sdk/prodigy_teams_pam_sdk/client/__init__.py
prodigy_teams_recipes_sdk/prodigy_teams_pam_sdk/client/action.py
prodigy_teams_recipes_sdk-0.1.24.dist-info/LICENSE
prodigy_teams_recipes_sdk-0.1.24.dist-info/METADATA
prodigy_teams_recipes_sdk-0.1.24.dist-info/WHEEL
prodigy_teams_recipes_sdk-0.1.24.dist-info/entry_points.txt
prodigy_teams_recipes_sdk-0.1.24.dist-info/top_level.txt
prodigy_teams_recipes_sdk-0.1.24.dist-info/RECORD
