Metadata-Version: 2.1
Name: prodigy-teams-recipes-sdk
Version: 0.1.24
Summary: Recipes SDK for Prodigy Teams
Home-page: https://prodi.gy
Author: ExplosionAI GmbH
Author-email: contact@explosion.ai
License: All rights reserved
License-File: LICENSE
Requires-Dist: cloudpathlib[gs,s3]>=0.10.0
Requires-Dist: confection>=0.1.0
Requires-Dist: email-validator
Requires-Dist: fastapi<=0.99,>=0.78
Requires-Dist: httpx
Requires-Dist: jsonschema
Requires-Dist: plotext==4.2.0
Requires-Dist: psycopg2-binary
Requires-Dist: pydantic<2.0.0,>1.10
Requires-Dist: pydantic[email]<2.0.0,>1.10
Requires-Dist: pyjwt
Requires-Dist: radicli>=0.0.25
Requires-Dist: spacy>=3.7
Requires-Dist: srsly>=2.4
Requires-Dist: typing-extensions>=4.7
Requires-Dist: uvicorn
